design_patterns/__init__.py
design_patterns/observer.py
design_patterns/singleton.py
design_patterns-0.2.0.dist-info/DESCRIPTION.rst
design_patterns-0.2.0.dist-info/METADATA
design_patterns-0.2.0.dist-info/metadata.json
design_patterns-0.2.0.dist-info/RECORD
design_patterns-0.2.0.dist-info/top_level.txt
design_patterns-0.2.0.dist-info/WHEEL
