Metadata-Version: 2.0
Name: design-patterns
Version: 0.2.0
Summary: Useful design patterns for Python
Home-page: https://github.com/victorlin/design-patterns
Author: Victor Lin
Author-email: hello@victorlin.me
License: MIT
Keywords: design patterns
Platform: UNKNOWN
Classifier: Programming Language :: Python :: 2
Classifier: Programming Language :: Python :: 3
Classifier: License :: OSI Approved :: MIT License
Classifier: Intended Audience :: Developers
Classifier: Programming Language :: Python
Requires-Dist: future
Provides-Extra: tests
Requires-Dist: pytest; extra == 'tests'
Requires-Dist: pytest-cov; extra == 'tests'
Requires-Dist: pytest-xdist; extra == 'tests'
Requires-Dist: pytest-capturelog; extra == 'tests'
